{
	"_version": "0.0.1",
	"_description": "algo",
	"user": {
		"photo": "https://imgur.com/UBhglrv",
		"name": "Javier Hernandez",
		"aboutMe": "Desarrollador web front-end. Diseño de páginas web y códificación. ",
		"socialNetwork": [
			{
				"name": "facebook",
				"urlLogo": "media/img/iconFacebook.png",
				"url": "https://www.facebook.com/error.error.404notfound"
			},
			{
				"name": "instagram",
				"urlLogo": "media/img/icon_instagram_.png",
				"url": "https://www.instagram.com/jav2332_/"
			},
			{
				"name": "github",
				"urlLogo": "media/img/icon_github.png",
				"url": "https://github.com/Javier09091"
			}
		]
	},
	"skills": {
		"technical": {
			"labels": [
				"Ingles (B2)",
				"Códificación",
				"Diseño web",
				"Conocimiento en algoritmos",
				"Modelado de base de datos"
			],
			"datasets": [
				{
					"label": "Soft skills",
					"data": [
						5,
						7,
						7,
						6,
						7
					],
					"backgroundColor": "rgba(255, 99, 132, 0.2)",
					"borderColor": "rgba(255, 99, 132, 1)",
					"borderWidth": 2
				}
			]
		},
		"soft": {
			"labels": [
				"Resolución de conflictos",
				"Autodidacta",
				"Comunicación efectiva",
				"Trabajo en equipo",
				"Creatividad"
			],
			"datasets": [
				{
					"label": "Technical skills",
					"data": [
						6,
						8,
						5,
						6,
						8
					],
					"backgroundColor": "rgba(255, 99, 132, 0.2)",
					"borderColor": "rgba(255, 99, 132, 1)",
					"borderWidth": 2
				}
			]
		}
	},
	"projects": [
		[
			{
				"id": "project_01",
				"name": "Intercopy",
				"description": "Diseño y codificación de un sitio web para una papelería.",
				"technologies": [
					"media/img/js.png",
					"media/img/css.png",
					"media/img/html.png",
					"media/img/php.png",
					"media/img/figma.png"
				],
				"image": "/media/img/papeleria.png"
			},
			{
				"id": "project_02",
				"name": "Reforma 22",
				"description": "Diseño y codificación de un sitio web para una escuela.",
				"technologies": [
					"media/img/js.png",
					"media/img/css.png",
					"media/img/html.png",
					"media/img/php.png",
					"media/img/figma.png"
				],
				"image": "media/img/escuela.png"
			}
		],
		[
			{
				"id": "project_03",
				"name": "Conexión de MySQL con JAVA",
				"description": "Codificación de un programa para conectar JAVA y MYSQL.",
				"technologies": [
					"media/img/java.png",
					"media/img/mysql.png"
				],
				"image": "media/img/java_bank.png"
			},
			{
				"id": "project_04",
				"name": "Portafolio fotografico",
				"description": "Diseño de una página web para visualizar fotografias.",
				"technologies": [
					"media/img/figma.png"
				],
				"image": "media/img/portafolio_foto.png"
			}
		],
		[
			{
				"id": "project_05",
				"name": "Calculadora",
				"description": "Diseño y desarrollo de una calculadora básica.",
				"technologies": [
					"media/img/figma.png",
					"media/img/js.png",
					"media/img/css.png",
					"media/img/html.png"
				],
				"image": "media/img/calculadora.png"
			},
			{
				"id": "project_06",
				"name": "Portafolio de proyectos",
				"description": "Diseño y desarrollo de una página web que muestra los proyectos de un desarrollador.",
				"technologies": [
					"media/img/figma.png",
					"media/img/react.png"
				],
				"image": "media/img/portafolio_react.png"
			}
		]
	]
}